futunn/__init__.py
futunn/client.py
futunn/constants.py
futunn/exceptions.py
futunn/models.py
futunn/token.py
futunn/urls.py
futunn_helper-2.0.0.dist-info/METADATA
futunn_helper-2.0.0.dist-info/WHEEL
futunn_helper-2.0.0.dist-info/licenses/LICENSE
futunn_helper-2.0.0.dist-info/RECORD
