Metadata-Version: 2.4
Name: futunn-helper
Version: 2.0.0
Summary: Asynchronous Python client for Futunn stock market quote API, inspired by py-googletrans
Project-URL: Homepage, https://github.com/karlorz/futunn-helper
Project-URL: Documentation, https://github.com/karlorz/futunn-helper/blob/main/README.md
Project-URL: Repository, https://github.com/karlorz/futunn-helper
Project-URL: Issues, https://github.com/karlorz/futunn-helper/issues
Author-email: Futunn Helper Contributors <futunn-helper@example.com>
License: MIT License
License-File: LICENSE
Keywords: api,async,finance,futunn,httpx,market,stock,trading
Classifier: Development Status :: 3 - Alpha
Classifier: Intended Audience :: Developers
Classifier: License :: OSI Approved :: MIT License
Classifier: Programming Language :: Python :: 3
Classifier: Programming Language :: Python :: 3.11
Classifier: Programming Language :: Python :: 3.12
Classifier: Programming Language :: Python :: 3.13
Classifier: Topic :: Office/Business :: Financial :: Investment
Classifier: Topic :: Software Development :: Libraries :: Python Modules
Requires-Python: >=3.11
Requires-Dist: httpx[http2]>=0.27.0
